sticky/__init__.py
sticky/sticky.py
stickynotes-1.0.0.data/scripts/initsticky
stickynotes-1.0.0.dist-info/METADATA
stickynotes-1.0.0.dist-info/WHEEL
stickynotes-1.0.0.dist-info/top_level.txt
stickynotes-1.0.0.dist-info/RECORD
