Metadata-Version: 2.1
Name: stickynotes
Version: 1.0.0
Summary: Sticky Notes
Home-page: http://github.com/veeshalsoni/sticky
Author: Vishal Soni
Author-email: vishal3soni@gmail.com
License: GPLv3
Keywords: StickyNotes Sticky Notes
Platform: UNKNOWN
Classifier: Development Status :: 5 - Production/Stable
Classifier: Programming Language :: Python
Classifier: Intended Audience :: End Users/Desktop
Classifier: License :: OSI Approved :: GNU General Public License v3 (GPLv3)
Requires-Dist: PySide2
